{"mean":{"confidence_interval":{"confidence_level":0.95,"lower_bound":573114.111305286,"upper_bound":582601.9341084568},"point_estimate":577996.9656472005,"standard_error":2430.3267502583485},"median":{"confidence_interval":{"confidence_level":0.95,"lower_bound":583124.4467073171,"upper_bound":587316.3921095008},"point_estimate":585316.6912220843,"standard_error":944.0447758122244},"median_abs_dev":{"confidence_interval":{"confidence_level":0.95,"lower_bound":7094.805463977577,"upper_bound":18290.180503768534},"point_estimate":12328.35441218063,"standard_error":2927.1541200096826},"slope":{"confidence_interval":{"confidence_level":0.95,"lower_bound":586553.8596208775,"upper_bound":592397.3981036218},"point_estimate":589490.6181232452,"standard_error":1494.2283140220927},"std_dev":{"confidence_interval":{"confidence_level":0.95,"lower_bound":20173.061836130353,"upper_bound":27746.887008493817},"point_estimate":24330.97331933666,"standard_error":1925.3448756771943}}