{"mean":{"confidence_interval":{"confidence_level":0.95,"lower_bound":7416521.50242857,"upper_bound":7462728.260607139},"point_estimate":7438450.671428573,"standard_error":11781.728195022846},"median":{"confidence_interval":{"confidence_level":0.95,"lower_bound":7396504.357142856,"upper_bound":7436633.285714285},"point_estimate":7415590.285714285,"standard_error":9669.262021226477},"median_abs_dev":{"confidence_interval":{"confidence_level":0.95,"lower_bound":64091.10246215499,"upper_bound":111492.68292060848},"point_estimate":82994.35802655571,"standard_error":11818.21936091757},"slope":null,"std_dev":{"confidence_interval":{"confidence_level":0.95,"lower_bound":83697.46573108004,"upper_bound":151586.50348273074},"point_estimate":118332.6693953806,"standard_error":17594.192137519705}}