{"mean":{"confidence_interval":{"confidence_level":0.95,"lower_bound":65434.51731817097,"upper_bound":66376.04305170331},"point_estimate":65903.00771154945,"standard_error":239.92645433695185},"median":{"confidence_interval":{"confidence_level":0.95,"lower_bound":65631.46989003694,"upper_bound":66698.16666666667},"point_estimate":66270.95976618066,"standard_error":248.72208261640264},"median_abs_dev":{"confidence_interval":{"confidence_level":0.95,"lower_bound":1594.8565456439735,"upper_bound":2798.4413217905544},"point_estimate":2172.2049112562913,"standard_error":307.40805328477614},"slope":{"confidence_interval":{"confidence_level":0.95,"lower_bound":65075.73003896521,"upper_bound":66146.22029972138},"point_estimate":65614.9140747377,"standard_error":273.387759571849},"std_dev":{"confidence_interval":{"confidence_level":0.95,"lower_bound":1973.4890675092206,"upper_bound":2874.108280498343},"point_estimate":2416.2144463970194,"standard_error":231.68492437938934}}