{"mean":{"confidence_interval":{"confidence_level":0.95,"lower_bound":89916.65862004377,"upper_bound":91223.60513111971},"point_estimate":90571.89421999062,"standard_error":332.937088466729},"median":{"confidence_interval":{"confidence_level":0.95,"lower_bound":89852.72146322779,"upper_bound":91255.25252525252},"point_estimate":90642.24319034709,"standard_error":379.7233485233264},"median_abs_dev":{"confidence_interval":{"confidence_level":0.95,"lower_bound":2518.724978462404,"upper_bound":4173.355906291038},"point_estimate":3385.77368424325,"standard_error":425.5100334600694},"slope":{"confidence_interval":{"confidence_level":0.95,"lower_bound":89521.63895651404,"upper_bound":91078.42694898356},"point_estimate":90268.04327659632,"standard_error":397.2661498780087},"std_dev":{"confidence_interval":{"confidence_level":0.95,"lower_bound":2851.6945155851954,"upper_bound":3822.6719728145013},"point_estimate":3355.387329633214,"standard_error":248.17720879411252}}