{"mean":{"confidence_interval":{"confidence_level":0.95,"lower_bound":809659.6309628796,"upper_bound":815306.255578231},"point_estimate":812505.441773787,"standard_error":1438.9509457949882},"median":{"confidence_interval":{"confidence_level":0.95,"lower_bound":807827.7555555556,"upper_bound":817759.1574074074},"point_estimate":812211.7448412699,"standard_error":2629.2349199772084},"median_abs_dev":{"confidence_interval":{"confidence_level":0.95,"lower_bound":12616.780511158882,"upper_bound":21142.58563206216},"point_estimate":16261.005389506892,"standard_error":2213.9313959642445},"slope":{"confidence_interval":{"confidence_level":0.95,"lower_bound":803434.4590812267,"upper_bound":809852.3183374356},"point_estimate":806591.089963056,"standard_error":1621.7765942100766},"std_dev":{"confidence_interval":{"confidence_level":0.95,"lower_bound":12891.168165974626,"upper_bound":15926.640146761163},"point_estimate":14513.413451026343,"standard_error":775.8292403185134}}