{"mean":{"confidence_interval":{"confidence_level":0.95,"lower_bound":53009.72345255813,"upper_bound":54456.80375386885},"point_estimate":53724.26828503053,"standard_error":368.92100034515386},"median":{"confidence_interval":{"confidence_level":0.95,"lower_bound":52005.6771189337,"upper_bound":53948.088314005356},"point_estimate":53058.630375481385,"standard_error":527.3750520272337},"median_abs_dev":{"confidence_interval":{"confidence_level":0.95,"lower_bound":2531.9838408712235,"upper_bound":4367.956021834085},"point_estimate":3478.938991928548,"standard_error":475.34043381864893},"slope":{"confidence_interval":{"confidence_level":0.95,"lower_bound":53072.06731286493,"upper_bound":54854.692580395495},"point_estimate":53938.76248108079,"standard_error":455.75076804822993},"std_dev":{"confidence_interval":{"confidence_level":0.95,"lower_bound":3124.615381952687,"upper_bound":4243.118748314385},"point_estimate":3715.5568624147,"standard_error":284.4017795263852}}