{"mean":{"confidence_interval":{"confidence_level":0.95,"lower_bound":481048.1888279435,"upper_bound":481341.5411177497},"point_estimate":481171.276274671,"standard_error":75.84831198053928},"median":{"confidence_interval":{"confidence_level":0.95,"lower_bound":480974.4173976608,"upper_bound":481189.8333333333},"point_estimate":481077.4264446794,"standard_error":55.095819463009676},"median_abs_dev":{"confidence_interval":{"confidence_level":0.95,"lower_bound":294.32052674380657,"upper_bound":482.13014344706687},"point_estimate":361.02392973147704,"standard_error":48.73640776082222},"slope":{"confidence_interval":{"confidence_level":0.95,"lower_bound":480994.1419722758,"upper_bound":481589.71843289636},"point_estimate":481212.76553273236,"standard_error":160.63269941743133},"std_dev":{"confidence_interval":{"confidence_level":0.95,"lower_bound":345.4039589047473,"upper_bound":1204.2533636212693},"point_estimate":764.4014688555789,"standard_error":280.0009823678706}}